tklinenums/__init__.py
tklinenums/tklinenums.py
tklinenums-1.7.0.dist-info/METADATA
tklinenums-1.7.0.dist-info/WHEEL
tklinenums-1.7.0.dist-info/top_level.txt
tklinenums-1.7.0.dist-info/RECORD
