Metadata-Version: 2.1
Name: tklinenums
Version: 1.7.0
Summary: A simple Tkinter widget for displaying line numbers
Home-page: https://github.com/Moosems/TkLineNums
Author: Moosems
Author-email: moosems.j@gmail.com
